sasapay/__init__.py
sasapay/auth/__init__.py
sasapay/auth/authentication.py
sasapay/payments/__init__.py
sasapay/payments/business_to_business.py
sasapay/payments/business_to_customer.py
sasapay/payments/customer_to_business.py
sasapay/utils/__init__.py
tests/__init__.py
tests/test_sasapay.py
sasapay_sdk-0.1.1.dist-info/LICENSE
sasapay_sdk-0.1.1.dist-info/METADATA
sasapay_sdk-0.1.1.dist-info/WHEEL
sasapay_sdk-0.1.1.dist-info/top_level.txt
sasapay_sdk-0.1.1.dist-info/RECORD
