Metadata-Version: 2.1
Name: sasapay-sdk
Version: 0.1.1
Summary: A Python wrapper for the SasaPay API
Home-page: https://github.com/sasapay/sasapay-python-sdk
Author: Simon Okello
Author-email: simonokello93@gmail.com
License: MIT
Classifier: Programming Language :: Python :: 3
Classifier: License :: OSI Approved :: MIT License
Classifier: Operating System :: OS Independent
Requires-Python: >=3.6
License-File: LICENSE
Requires-Dist: requests
